grapycal/__init__.py
grapycal/__main__.py
grapycal/app.py
grapycal/core/__init__.py
grapycal/core/background_runner.py
grapycal/core/local.py
grapycal/core/running_module.py
grapycal/core/stdout_helper.py
grapycal/core/workspace.py
grapycal/extension/__init__.py
grapycal/extension/extension.py
grapycal/extension/extensionManager.py
grapycal/extension/extensionSearch.py
grapycal/extension/utils.py
grapycal/extension_api/utils.py
grapycal/sobjects/__init__.py
grapycal/sobjects/controls/__init__.py
grapycal/sobjects/controls/buttonControl.py
grapycal/sobjects/controls/control.py
grapycal/sobjects/controls/imageControl.py
grapycal/sobjects/controls/linePlotControl.py
grapycal/sobjects/controls/nullControl.py
grapycal/sobjects/controls/optionControl.py
grapycal/sobjects/controls/textControl.py
grapycal/sobjects/controls/threeControl.py
grapycal/sobjects/DVfunctionNode.py
grapycal/sobjects/edge.py
grapycal/sobjects/editor.py
grapycal/sobjects/fileView.py
grapycal/sobjects/functionNode.py
grapycal/sobjects/node.py
grapycal/sobjects/port.py
grapycal/sobjects/settings.py
grapycal/sobjects/sidebar.py
grapycal/sobjects/sourceNode.py
grapycal/sobjects/workspaceObject.py
grapycal/utils/__init__.py
grapycal/utils/config.py
grapycal/utils/file.py
grapycal/utils/httpResource.py
grapycal/utils/io.py
grapycal/utils/logging.py
grapycal/utils/misc.py
grapycal/utils/nodeGen.py
grapycal/utils/usersettings.py
grapycal/webpage/click.mp3
grapycal/webpage/click0.mp3
grapycal/webpage/css/base.css
grapycal/webpage/css/blocks/edge.css
grapycal/webpage/css/blocks/main.css
grapycal/webpage/css/blocks/node.css
grapycal/webpage/css/blocks/port.css
grapycal/webpage/css/blocks/workspace.css
grapycal/webpage/css/dynamic.css
grapycal/webpage/css/fire/main.css
grapycal/webpage/css/light/edge.css
grapycal/webpage/css/light/main.css
grapycal/webpage/css/light/node.css
grapycal/webpage/css/light/port.css
grapycal/webpage/css/light/workspace.css
grapycal/webpage/css/main.css
grapycal-0.11.3.dist-info/entry_points.txt
grapycal-0.11.3.dist-info/METADATA
grapycal-0.11.3.dist-info/WHEEL
grapycal-0.11.3.dist-info/RECORD
