Metadata-Version: 2.1
Name: grapycal
Version: 0.11.3
Summary: A highly interactive visual programming language
License: BSD-3-Clause
Author: eri24816
Author-email: a931eric@gmail.com
Maintainer: eri24816
Maintainer-email: a931eric@gmail.com
Requires-Python: >=3.11,<4.0
Classifier: License :: OSI Approved :: BSD License
Classifier: Programming Language :: Python :: 3
Classifier: Programming Language :: Python :: 3.11
Requires-Dist: aiohttp (>=3.9.1,<4.0.0)
Requires-Dist: certifi (>=2023.11.17,<2024.0.0)
Requires-Dist: dacite (>=1.8.1,<2.0.0)
Requires-Dist: objectsync (>=0.9.2)
Requires-Dist: pyyaml (>=6.0,<7.0)
Requires-Dist: toml (>=0.10.2,<0.11.0)
Requires-Dist: usersettings (>=1.1.5,<2.0.0)
Project-URL: Documentation, https://docs.grapycal.org/
